shoehorn/__init__.py
shoehorn/compat.py
shoehorn/event.py
shoehorn/logger.py
shoehorn/stdlib.py
shoehorn-0.2.3.dist-info/DESCRIPTION.rst
shoehorn-0.2.3.dist-info/METADATA
shoehorn-0.2.3.dist-info/RECORD
shoehorn-0.2.3.dist-info/WHEEL
shoehorn-0.2.3.dist-info/metadata.json
shoehorn-0.2.3.dist-info/top_level.txt
