Metadata-Version: 2.0
Name: shoehorn
Version: 0.2.3
Summary: Shoehorn structured logs into or out of standard library logging
Home-page: https://github.com/cjw296/shoehorn
Author: Chris Withers
Author-email: chris@withers.org
License: MIT
Platform: UNKNOWN
Classifier: Intended Audience :: Developers
Classifier: License :: OSI Approved :: MIT License
Classifier: Programming Language :: Python :: 2
Classifier: Programming Language :: Python :: 2.7
Classifier: Programming Language :: Python :: 3
Classifier: Programming Language :: Python :: 3.4
Classifier: Programming Language :: Python :: 3.5
Provides-Extra: build
Requires-Dist: sphinx; extra == 'build'
Requires-Dist: pkginfo; extra == 'build'
Requires-Dist: setuptools-git; extra == 'build'
Requires-Dist: twine; extra == 'build'
Requires-Dist: wheel; extra == 'build'
Provides-Extra: test
Requires-Dist: coveralls; extra == 'test'
Requires-Dist: manuel; extra == 'test'
Requires-Dist: nose; extra == 'test'
Requires-Dist: nose-cov; extra == 'test'
Requires-Dist: nose-fixes; extra == 'test'
Requires-Dist: testfixtures; extra == 'test'
